[{"name":"CENG 1","sections":[{"type":"lecture","sectionID":"883322","section":"A00","days":"W","time":"5:00p-5:50p","location":"PETER 102","teacher":"Talbot, Jan B","openSeats":0,"seatLimit":27,"waitlistSize":2,"isEnrollable":true}]},{"name":"CENG 4","sections":[{"type":"lecture","sectionID":null,"section":"A00","days":"M","time":"4:00p-4:50p","location":"CENTR 212","teacher":"Drews, Aaron","openSeats":null,"seatLimit":null,"waitlistSize":null,"isEnrollable":false},{"type":"lab","sectionID":"883324","section":"A01","days":"M","time":"2:00p-3:50p","location":"SME 305","teacher":"Drews, Aaron","openSeats":6,"seatLimit":27,"waitlistSize":0,"isEnrollable":true},{"type":"lab","sectionID":"883325","section":"A02","days":"W","time":"2:00p-3:50p","location":"SME 305","teacher":"Drews, Aaron","openSeats":8,"seatLimit":27,"waitlistSize":0,"isEnrollable":true},{"type":"lab","sectionID":"883326","section":"A03","days":"F","time":"2:00p-3:50p","location":"SME 305","teacher":"Drews, Aaron","openSeats":14,"seatLimit":27,"waitlistSize":0,"isEnrollable":true}]},{"name":"CENG 15","sections":[{"type":"lecture","sectionID":"883314","section":"A00","days":"TuTh","time":"9:30a-10:50a","location":"EBU2 203","teacher":"Drews, Aaron","openSeats":0,"seatLimit":17,"waitlistSize":1,"isEnrollable":true},{"type":"final","sectionID":null,"section":null,"days":"12/08/2016 Th","time":"8:00a-10:59a","location":"TBA","teacher":null,"openSeats":null,"seatLimit":null,"waitlistSize":null,"isEnrollable":false},{"type":"lecture","sectionID":"883315","section":"B00","days":"TuTh","time":"11:00a-12:20p","location":"EBU2 203","teacher":"Drews, Aaron","openSeats":0,"seatLimit":17,"waitlistSize":2,"isEnrollable":true},{"type":"final","sectionID":null,"section":null,"days":"12/07/2016 W","time":"11:30a-2:29p","location":"TBA","teacher":null,"openSeats":null,"seatLimit":null,"waitlistSize":null,"isEnrollable":false},{"type":"lecture","sectionID":"883316","section":"C00","days":"TuTh","time":"2:00p-3:20p","location":"EBU2 203","teacher":"Drews, Aaron","openSeats":0,"seatLimit":17,"waitlistSize":1,"isEnrollable":true},{"type":"final","sectionID":null,"section":null,"days":"12/08/2016 Th","time":"3:00p-5:59p","location":"TBA","teacher":null,"openSeats":null,"seatLimit":null,"waitlistSize":null,"isEnrollable":false}]},{"name":"CENG 100","sections":[{"type":"lecture","sectionID":"884054","section":"B00","days":"MWF","time":"10:00a-10:50a","location":"PCYNH 106","teacher":"Talbot, Jan B","openSeats":10,"seatLimit":156,"waitlistSize":0,"isEnrollable":true},{"type":"final","sectionID":null,"section":null,"days":"12/09/2016 F","time":"8:00a-10:59a","location":"TBA","teacher":null,"openSeats":null,"seatLimit":null,"waitlistSize":null,"isEnrollable":false}]},{"name":"CENG 101A","sections":[{"type":"lecture","sectionID":"883329","section":"A00","days":"TuTh","time":"9:30a-10:50a","location":"PCYNH 106","teacher":"Miller, David R.","openSeats":6,"seatLimit":183,"waitlistSize":0,"isEnrollable":true},{"type":"final","sectionID":null,"section":null,"days":"12/08/2016 Th","time":"8:00a-10:59a","location":"TBA","teacher":null,"openSeats":null,"seatLimit":null,"waitlistSize":null,"isEnrollable":false}]},{"name":"CENG 120","sections":[{"type":"lecture","sectionID":"883330","section":"A00","days":"MWF","time":"3:00p-3:50p","location":"WLH 2001","teacher":"Opatkiewicz, Justin Paul","openSeats":6,"seatLimit":250,"waitlistSize":0,"isEnrollable":true},{"type":"final","sectionID":null,"section":null,"days":"12/09/2016 F","time":"3:00p-5:59p","location":"TBA","teacher":null,"openSeats":null,"seatLimit":null,"waitlistSize":null,"isEnrollable":false}]},{"name":"CENG 122","sections":[{"type":"lecture","sectionID":"883331","section":"A00","days":"TuTh","time":"3:30p-4:50p","location":"WLH 2001","teacher":"Opatkiewicz, Justin Paul","openSeats":11,"seatLimit":250,"waitlistSize":0,"isEnrollable":true},{"type":"final","sectionID":null,"section":null,"days":"12/05/2016 M","time":"3:00p-5:59p","location":"TBA","teacher":null,"openSeats":null,"seatLimit":null,"waitlistSize":null,"isEnrollable":false}]},{"name":"CENG 199","sections":[{"type":"independentStudy","sectionID":"888607","section":"001","days":"TBA","time":"TBA","location":"TBA","teacher":"Lipomi, Darren John","openSeats":1,"seatLimit":3,"waitlistSize":0,"isEnrollable":true},{"type":"independentStudy","sectionID":"895241","section":"002","days":"TBA","time":"TBA","location":"TBA","teacher":"Bandaru, Prabhakar","openSeats":1,"seatLimit":1,"waitlistSize":0,"isEnrollable":true},{"type":"independentStudy","sectionID":"895643","section":"003","days":"TBA","time":"TBA","location":"TBA","teacher":"Sah, Robert Lie- Yuan","openSeats":0,"seatLimit":1,"waitlistSize":0,"isEnrollable":true},{"type":"independentStudy","sectionID":"895777","section":"004","days":"TBA","time":"TBA","location":"TBA","teacher":"Chen, Renkun","openSeats":0,"seatLimit":1,"waitlistSize":0,"isEnrollable":true},{"type":"independentStudy","sectionID":"896890","section":"005","days":"TBA","time":"TBA","location":"TBA","teacher":"Liu, Ping","openSeats":0,"seatLimit":1,"waitlistSize":0,"isEnrollable":true}]},{"name":"CENG 205","sections":[{"type":"seminar","sectionID":"883317","section":"A00","days":"W","time":"11:00a-12:00p","location":"SME 248","teacher":"Talbot, Jan B","openSeats":38,"seatLimit":100,"waitlistSize":0,"isEnrollable":true}]},{"name":"CENG 210A","sections":[{"type":"lecture","sectionID":"882819","section":"A00","days":"TuTh","time":"3:30p-4:50p","location":"CSB 002","teacher":"Krasheninnikov, Sergei","openSeats":10,"seatLimit":40,"waitlistSize":0,"isEnrollable":true},{"type":"final","sectionID":null,"section":null,"days":"12/05/2016 M","time":"3:00p-5:59p","location":"TBA","teacher":null,"openSeats":null,"seatLimit":null,"waitlistSize":null,"isEnrollable":false}]},{"name":"CENG 211","sections":[{"type":"lecture","sectionID":"883318","section":"A00","days":"TuTh","time":"2:00p-3:20p","location":"WLH 2204","teacher":"Chen, Yi","openSeats":1,"seatLimit":25,"waitlistSize":0,"isEnrollable":true},{"type":"final","sectionID":null,"section":null,"days":"12/08/2016 Th","time":"3:00p-5:59p","location":"TBA","teacher":null,"openSeats":null,"seatLimit":null,"waitlistSize":null,"isEnrollable":false}]},{"name":"CENG 212","sections":[{"type":"lecture","sectionID":"883319","section":"A00","days":"TuTh","time":"9:30a-10:50a","location":"WLH 2204","teacher":"Lipomi, Darren John","openSeats":15,"seatLimit":25,"waitlistSize":0,"isEnrollable":true},{"type":"final","sectionID":null,"section":null,"days":"12/08/2016 Th","time":"8:00a-10:59a","location":"TBA","teacher":null,"openSeats":null,"seatLimit":null,"waitlistSize":null,"isEnrollable":false}]},{"name":"CENG 221A","sections":[{"type":"lecture","sectionID":"882818","section":"A00","days":"TuTh","time":"12:30p-1:50p","location":"CSB 004","teacher":"Liu, Ping","openSeats":9,"seatLimit":40,"waitlistSize":0,"isEnrollable":true},{"type":"final","sectionID":null,"section":null,"days":"12/09/2016 F","time":"11:30a-2:29p","location":"TBA","teacher":null,"openSeats":null,"seatLimit":null,"waitlistSize":null,"isEnrollable":false}]},{"name":"CENG 299","sections":[{"type":"independentStudy","sectionID":"883709","section":"001","days":"TBA","time":"TBA","location":"TBA","teacher":"Lipomi, Darren John","openSeats":-1,"seatLimit":-1,"waitlistSize":0,"isEnrollable":true},{"type":"independentStudy","sectionID":"883711","section":"002","days":"TBA","time":"TBA","location":"TBA","teacher":"Meng, Y. Shirley","openSeats":-1,"seatLimit":-1,"waitlistSize":0,"isEnrollable":true},{"type":"independentStudy","sectionID":"883712","section":"003","days":"TBA","time":"TBA","location":"TBA","teacher":"Luo, Jian","openSeats":-1,"seatLimit":-1,"waitlistSize":0,"isEnrollable":true},{"type":"independentStudy","sectionID":"883713","section":"004","days":"TBA","time":"TBA","location":"TBA","teacher":"Vazquez Mena, Oscar","openSeats":-1,"seatLimit":-1,"waitlistSize":0,"isEnrollable":true},{"type":"independentStudy","sectionID":"883753","section":"005","days":"TBA","time":"TBA","location":"TBA","teacher":"Sirbuly, Donald","openSeats":-1,"seatLimit":-1,"waitlistSize":0,"isEnrollable":true},{"type":"independentStudy","sectionID":"883754","section":"006","days":"TBA","time":"TBA","location":"TBA","teacher":"Zhang, Liangfang","openSeats":-1,"seatLimit":-1,"waitlistSize":0,"isEnrollable":true},{"type":"independentStudy","sectionID":"883755","section":"007","days":"TBA","time":"TBA","location":"TBA","teacher":"Palsson, Bernhard O.","openSeats":-1,"seatLimit":-1,"waitlistSize":0,"isEnrollable":true},{"type":"independentStudy","sectionID":"883756","section":"008","days":"TBA","time":"TBA","location":"TBA","teacher":"Rangamani, Padmini","openSeats":-1,"seatLimit":-1,"waitlistSize":0,"isEnrollable":true},{"type":"independentStudy","sectionID":"883831","section":"009","days":"TBA","time":"TBA","location":"TBA","teacher":"Almutairi, Adah","openSeats":-1,"seatLimit":-1,"waitlistSize":0,"isEnrollable":true},{"type":"independentStudy","sectionID":"883832","section":"010","days":"TBA","time":"TBA","location":"TBA","teacher":"Arya, Gaurav","openSeats":-1,"seatLimit":-1,"waitlistSize":0,"isEnrollable":true},{"type":"independentStudy","sectionID":"883833","section":"011","days":"TBA","time":"TBA","location":"TBA","teacher":"Lo, Yu- Hwa","openSeats":-1,"seatLimit":-1,"waitlistSize":0,"isEnrollable":true},{"type":"independentStudy","sectionID":"883976","section":"012","days":"TBA","time":"TBA","location":"TBA","teacher":"Esener, Sadik C","openSeats":-1,"seatLimit":-1,"waitlistSize":0,"isEnrollable":true},{"type":"independentStudy","sectionID":"884043","section":"013","days":"TBA","time":"TBA","location":"TBA","teacher":"Kummel, Andrew C","openSeats":-1,"seatLimit":-1,"waitlistSize":0,"isEnrollable":true},{"type":"independentStudy","sectionID":"884064","section":"014","days":"TBA","time":"TBA","location":"TBA","teacher":"Yang, Kesong","openSeats":-1,"seatLimit":-1,"waitlistSize":0,"isEnrollable":true},{"type":"independentStudy","sectionID":"884561","section":"015","days":"TBA","time":"TBA","location":"TBA","teacher":"Heller, Michael J","openSeats":-1,"seatLimit":-1,"waitlistSize":0,"isEnrollable":true}]}]
