[{"name":"HLAW 207A","sections":[{"type":"lecture","sectionID":"884611","section":"A00","days":"W","time":"5:30p-9:00p","location":"TBA TBA","teacher":"Mackey, Timothy Ken","openSeats":"Unlim","seatLimit":null,"waitlistSize":0,"isEnrollable":true},{"type":"final","sectionID":null,"section":null,"days":"12/08/2016 Th","time":"7:00p-9:59p","location":"TBA","teacher":null,"openSeats":null,"seatLimit":null,"waitlistSize":null,"isEnrollable":false}]},{"name":"HLAW 211","sections":[{"type":"lecture","sectionID":"884606","section":"A00","days":"M","time":"5:30p-8:30p","location":"TBA TBA","teacher":"Mackey, Timothy Ken","openSeats":"Unlim","seatLimit":null,"waitlistSize":0,"isEnrollable":true},{"type":"final","sectionID":null,"section":null,"days":"12/08/2016 Th","time":"7:00p-9:59p","location":"TBA","teacher":null,"openSeats":null,"seatLimit":null,"waitlistSize":null,"isEnrollable":false}]},{"name":"HLAW 214","sections":[{"type":"independentStudy","sectionID":"884607","section":"A00","days":"TBA","time":"TBA","location":"TBA","teacher":"Mackey, Timothy Ken","openSeats":-1,"seatLimit":-1,"waitlistSize":0,"isEnrollable":true}]},{"name":"HLAW 215","sections":[{"type":"lecture","sectionID":"884608","section":"A00","days":"Th","time":"5:30p-8:30p","location":"TBA TBA","teacher":"Mackey, Timothy Ken","openSeats":3,"seatLimit":20,"waitlistSize":0,"isEnrollable":true},{"type":"final","sectionID":null,"section":null,"days":"12/09/2016 F","time":"7:00p-9:59p","location":"TBA","teacher":null,"openSeats":null,"seatLimit":null,"waitlistSize":null,"isEnrollable":false}]},{"name":"HLAW 298","sections":[{"type":"seminar","sectionID":"884609","section":"A00","days":"TBA","time":"TBA","location":"TBA","teacher":"Mackey, Timothy Ken","openSeats":-1,"seatLimit":-1,"waitlistSize":0,"isEnrollable":true}]},{"name":"HLAW 298A","sections":[{"type":"seminar","sectionID":"884612","section":"A00","days":"Tu","time":"5:30p-7:30p","location":"TBA TBA","teacher":"Devereaux, Mary L.","openSeats":"Unlim","seatLimit":null,"waitlistSize":0,"isEnrollable":true}]},{"name":"HLAW 299","sections":[{"type":"independentStudy","sectionID":"884610","section":"A00","days":"TBA","time":"TBA","location":"TBA","teacher":"Mackey, Timothy Ken","openSeats":-1,"seatLimit":-1,"waitlistSize":0,"isEnrollable":true}]}]
